{
	"erddap_url": "https://erddap.dataexplorer.oceanobservatories.org/erddap/tabledap/",
	"mooring_id": "ce02shbp",
	"current_deployment": {
		"number": 8,
		"startdate": "2021-08-23T19:27:00Z",
		"depth": 80,
		"latitude": 44.63720995,
		"longitude": -124.3054578
	},
	"nodes": {
		"bep": {
			"ctdbp": {
				"reference_designator": "CE02SHBP-LJ01D-06-CTDBPN106",
				"erddap_id": "ooi-ce02shbp-lj01d-06-ctdbpn106",
				"z_coordinate": -80,
				"decimation_factor": 1,
				"variable_names": {
					"sea_water_temperature": "sea_water_temperature",
					"sea_water_salinity": "sea_water_practical_salinity",
					"sea_water_electrical_conductivity": "sea_water_electrical_conductivity",
					"sea_water_pressure": "sea_water_pressure",
					"sea_water_density": "sea_water_density"
				},
				"variable_units": {
					"sea_water_temperature": "degree_C",
					"sea_water_salinity": "1",
					"sea_water_electrical_conductivity": "S m-1",
					"sea_water_pressure": "dbar",
					"sea_water_density": "kg m-3"
				}
			},
			"dosta": {
				"reference_designator": "CE02SHBP-LJ01D-06-DOSTAD106",
				"erddap_id": "ooi-ce02shbp-lj01d-06-dostad106",
				"z_coordinate": -80,
				"decimation_factor": 1,
				"variable_names": {
					"mass_concentration_of_oxygen_in_sea_water": "mole_concentration_of_dissolved_molecular_oxygen_in_sea_water"
				},
				"variable_units": {
					"mass_concentration_of_oxygen_in_sea_water": "umol L-1"
				}
			},
			"phsen": {
				"reference_designator": "CE02SHBP-LJ01D-10-PHSEND103",
				"erddap_id": "ooi-ce02shbp-lj01d-10-phsend103",
				"z_coordinate": -80,
				"decimation_factor": 1,
				"variable_names": {
					"sea_water_ph_reported_on_total_scale": "sea_water_ph_reported_on_total_scale"
				},
				"variable_units": {
					"sea_water_ph_reported_on_total_scale": "1"
				}
			},
			"pco2w": {
				"reference_designator": "CE02SHBP-LJ01D-09-PCO2WB103",
				"erddap_id": "ooi-ce02shbp-lj01d-09-pco2wb103",
				"z_coordinate": -80,
				"decimation_factor": 1,
				"variable_names": {
					"partial_pressure_of_carbon_dioxide_in_sea_water": "partial_pressure_of_carbon_dioxide_in_sea_water"
				},
				"variable_units": {
					"partial_pressure_of_carbon_dioxide_in_sea_water": "uatm"
				}
			}
		}
	}
}
